{
  "updated": "2026-05-29T14:39:15.900Z",
  "period": "May 27 – May 29",
  "lookbackDays": 5,
  "strategies": [
    "mlb_laser_1",
    "mlb_laser_2",
    "mlb_laser_3"
  ],
  "summary": {
    "wins": 9,
    "losses": 6,
    "winRate": 60,
    "startBalance": 100,
    "endBalance": 99,
    "days": 3,
    "gameCount": 15,
    "avgWinPnl": 65.76,
    "avgLossPnl": -98.82,
    "totalWon": 591.81,
    "totalLost": 592.9
  },
  "featured": [
    {
      "game": "Braves vs Red Sox",
      "date": "May 29",
      "pnl": 75.63,
      "pct": 75.6,
      "result": "win",
      "away": "atl",
      "home": "bos",
      "model": "mlb_laser_2",
      "laser": "Laser 2"
    },
    {
      "game": "Angels vs Tigers",
      "date": "May 28",
      "pnl": -92.9,
      "pct": -92.9,
      "result": "loss",
      "away": "laa",
      "home": "det",
      "model": "mlb_laser_3",
      "laser": "Laser 3"
    },
    {
      "game": "Yankees vs Royals",
      "date": "May 28",
      "pnl": 67.8,
      "pct": 67.8,
      "result": "win",
      "away": "nyy",
      "home": "kc",
      "model": "mlb_laser_3",
      "laser": "Laser 3"
    },
    {
      "game": "Astros vs Rangers",
      "date": "May 28",
      "pnl": -100,
      "pct": -101.1,
      "result": "loss",
      "away": "hou",
      "home": "tex",
      "model": "mlb_laser_3",
      "laser": "Laser 3"
    },
    {
      "game": "Reds vs Mets",
      "date": "May 28",
      "pnl": 71.56,
      "pct": 71.6,
      "result": "win",
      "away": "cin",
      "home": "nym",
      "model": "mlb_laser_3",
      "laser": "Laser 3"
    },
    {
      "game": "Cubs vs Pirates",
      "date": "May 28",
      "pnl": 69.12,
      "pct": 69.1,
      "result": "win",
      "away": "chc",
      "home": "pit",
      "model": "mlb_laser_2",
      "laser": "Laser 2"
    },
    {
      "game": "Twins vs White Sox",
      "date": "May 28",
      "pnl": -100,
      "pct": -101.2,
      "result": "loss",
      "away": "min",
      "home": "chw",
      "model": "mlb_laser_1",
      "laser": "Laser 1"
    },
    {
      "game": "Braves vs Red Sox",
      "date": "May 28",
      "pnl": -100,
      "pct": -110.5,
      "result": "loss",
      "away": "atl",
      "home": "bos",
      "model": "mlb_laser_2",
      "laser": "Laser 2"
    },
    {
      "game": "Rays vs Orioles",
      "date": "May 28",
      "pnl": -100,
      "pct": -102.9,
      "result": "loss",
      "away": "tb",
      "home": "bal",
      "model": "mlb_laser_3",
      "laser": "Laser 3"
    },
    {
      "game": "Cardinals vs Brewers",
      "date": "May 27",
      "pnl": 49.42,
      "pct": 49.4,
      "result": "win",
      "away": "stl",
      "home": "mil",
      "model": "mlb_laser_2",
      "laser": "Laser 2"
    },
    {
      "game": "Nationals vs Guardians",
      "date": "May 27",
      "pnl": -100,
      "pct": -100.4,
      "result": "loss",
      "away": "wsh",
      "home": "cle",
      "model": "mlb_laser_2",
      "laser": "Laser 2"
    },
    {
      "game": "AZ vs Giants",
      "date": "May 27",
      "pnl": 62.77,
      "pct": 62.8,
      "result": "win",
      "away": "az",
      "home": "sf",
      "model": "mlb_laser_2",
      "laser": "Laser 2"
    },
    {
      "game": "Mariners vs ATH",
      "date": "May 27",
      "pnl": 39.95,
      "pct": 40,
      "result": "win",
      "away": "sea",
      "home": "ath",
      "model": "mlb_laser_2",
      "laser": "Laser 2"
    },
    {
      "game": "Nationals vs Guardians",
      "date": "May 27",
      "pnl": 72.99,
      "pct": 73,
      "result": "win",
      "away": "wsh",
      "home": "cle",
      "model": "mlb_laser_2",
      "laser": "Laser 2"
    },
    {
      "game": "Reds vs Mets",
      "date": "May 27",
      "pnl": 82.57,
      "pct": 82.6,
      "result": "win",
      "away": "cin",
      "home": "nym",
      "model": "mlb_laser_3",
      "laser": "Laser 3"
    }
  ],
  "feed": [
    {
      "game": "ATL vs BOS",
      "pnl": 75.63,
      "pct": 75.6,
      "result": "win",
      "away": "atl",
      "home": "bos",
      "model": "mlb_laser_2",
      "laser": "Laser 2"
    },
    {
      "game": "LAA vs DET",
      "pnl": -92.9,
      "pct": -92.9,
      "result": "loss",
      "away": "laa",
      "home": "det",
      "model": "mlb_laser_3",
      "laser": "Laser 3"
    },
    {
      "game": "NYY vs KC",
      "pnl": 67.8,
      "pct": 67.8,
      "result": "win",
      "away": "nyy",
      "home": "kc",
      "model": "mlb_laser_3",
      "laser": "Laser 3"
    },
    {
      "game": "HOU vs TEX",
      "pnl": -100,
      "pct": -101.1,
      "result": "loss",
      "away": "hou",
      "home": "tex",
      "model": "mlb_laser_3",
      "laser": "Laser 3"
    },
    {
      "game": "CIN vs NYM",
      "pnl": 71.56,
      "pct": 71.6,
      "result": "win",
      "away": "cin",
      "home": "nym",
      "model": "mlb_laser_3",
      "laser": "Laser 3"
    },
    {
      "game": "CHC vs PIT",
      "pnl": 69.12,
      "pct": 69.1,
      "result": "win",
      "away": "chc",
      "home": "pit",
      "model": "mlb_laser_2",
      "laser": "Laser 2"
    },
    {
      "game": "MIN vs CWS",
      "pnl": -100,
      "pct": -101.2,
      "result": "loss",
      "away": "min",
      "home": "chw",
      "model": "mlb_laser_1",
      "laser": "Laser 1"
    },
    {
      "game": "ATL vs BOS",
      "pnl": -100,
      "pct": -110.5,
      "result": "loss",
      "away": "atl",
      "home": "bos",
      "model": "mlb_laser_2",
      "laser": "Laser 2"
    },
    {
      "game": "TB vs BAL",
      "pnl": -100,
      "pct": -102.9,
      "result": "loss",
      "away": "tb",
      "home": "bal",
      "model": "mlb_laser_3",
      "laser": "Laser 3"
    },
    {
      "game": "STL vs MIL",
      "pnl": 49.42,
      "pct": 49.4,
      "result": "win",
      "away": "stl",
      "home": "mil",
      "model": "mlb_laser_2",
      "laser": "Laser 2"
    },
    {
      "game": "WSH vs CLE",
      "pnl": -100,
      "pct": -100.4,
      "result": "loss",
      "away": "wsh",
      "home": "cle",
      "model": "mlb_laser_2",
      "laser": "Laser 2"
    },
    {
      "game": "AZ vs SF",
      "pnl": 62.77,
      "pct": 62.8,
      "result": "win",
      "away": "az",
      "home": "sf",
      "model": "mlb_laser_2",
      "laser": "Laser 2"
    },
    {
      "game": "SEA vs ATH",
      "pnl": 39.95,
      "pct": 40,
      "result": "win",
      "away": "sea",
      "home": "ath",
      "model": "mlb_laser_2",
      "laser": "Laser 2"
    },
    {
      "game": "WSH vs CLE",
      "pnl": 72.99,
      "pct": 73,
      "result": "win",
      "away": "wsh",
      "home": "cle",
      "model": "mlb_laser_2",
      "laser": "Laser 2"
    },
    {
      "game": "CIN vs NYM",
      "pnl": 82.57,
      "pct": 82.6,
      "result": "win",
      "away": "cin",
      "home": "nym",
      "model": "mlb_laser_3",
      "laser": "Laser 3"
    }
  ]
}
